<?xml version='1.0' encoding='utf-8'?>
<tv>
  <channel id="龍華卡通台">
    <display-name>龍華卡通台</display-name>
  </channel>
  <programme start="20260117233000 +0800" stop="20260118000000 +0800" channel="龍華卡通台">
    <title>森林偵探</title>
    <desc></desc>
  </programme>
  <programme start="20260118000000 +0800" stop="20260118003000 +0800" channel="龍華卡通台">
    <title>南瓜入侵</title>
    <desc></desc>
  </programme>
  <programme start="20260118003000 +0800" stop="20260118010000 +0800" channel="龍華卡通台">
    <title>南瓜入侵</title>
    <desc></desc>
  </programme>
  <programme start="20260118010000 +0800" stop="20260118013000 +0800" channel="龍華卡通台">
    <title>森林偵探</title>
    <desc></desc>
  </programme>
  <programme start="20260118013000 +0800" stop="20260118020000 +0800" channel="龍華卡通台">
    <title>森林偵探</title>
    <desc></desc>
  </programme>
  <programme start="20260118020000 +0800" stop="20260118023000 +0800" channel="龍華卡通台">
    <title>呱張爆音團</title>
    <desc></desc>
  </programme>
  <programme start="20260118023000 +0800" stop="20260118030000 +0800" channel="龍華卡通台">
    <title>呱張爆音團</title>
    <desc></desc>
  </programme>
  <programme start="20260118030000 +0800" stop="20260118033000 +0800" channel="龍華卡通台">
    <title>呱張爆音團</title>
    <desc></desc>
  </programme>
  <programme start="20260118033000 +0800" stop="20260118040000 +0800" channel="龍華卡通台">
    <title>呱張爆音團</title>
    <desc></desc>
  </programme>
  <programme start="20260118040000 +0800" stop="20260118043000 +0800" channel="龍華卡通台">
    <title>豆小鴨</title>
    <desc></desc>
  </programme>
  <programme start="20260118043000 +0800" stop="20260118050000 +0800" channel="龍華卡通台">
    <title>豆小鴨</title>
    <desc></desc>
  </programme>
  <programme start="20260118050000 +0800" stop="20260118053000 +0800" channel="龍華卡通台">
    <title>森林偵探</title>
    <desc></desc>
  </programme>
  <programme start="20260118053000 +0800" stop="20260118060000 +0800" channel="龍華卡通台">
    <title>森林偵探</title>
    <desc></desc>
  </programme>
  <programme start="20260118060000 +0800" stop="20260118063000 +0800" channel="龍華卡通台">
    <title>呱張爆音團</title>
    <desc></desc>
  </programme>
  <programme start="20260118063000 +0800" stop="20260118070000 +0800" channel="龍華卡通台">
    <title>呱張爆音團</title>
    <desc></desc>
  </programme>
  <programme start="20260118070000 +0800" stop="20260118073000 +0800" channel="龍華卡通台">
    <title>呱張爆音團</title>
    <desc></desc>
  </programme>
  <programme start="20260118073000 +0800" stop="20260118080000 +0800" channel="龍華卡通台">
    <title>呱張爆音團</title>
    <desc></desc>
  </programme>
  <programme start="20260118080000 +0800" stop="20260118083000 +0800" channel="龍華卡通台">
    <title>南瓜入侵</title>
    <desc></desc>
  </programme>
  <programme start="20260118083000 +0800" stop="20260118090000 +0800" channel="龍華卡通台">
    <title>南瓜入侵</title>
    <desc></desc>
  </programme>
  <programme start="20260118090000 +0800" stop="20260118093000 +0800" channel="龍華卡通台">
    <title>豆小鴨</title>
    <desc></desc>
  </programme>
  <programme start="20260118093000 +0800" stop="20260118100000 +0800" channel="龍華卡通台">
    <title>豆小鴨</title>
    <desc></desc>
  </programme>
  <programme start="20260118100000 +0800" stop="20260118103000 +0800" channel="龍華卡通台">
    <title>森林偵探</title>
    <desc></desc>
  </programme>
  <programme start="20260118103000 +0800" stop="20260118110000 +0800" channel="龍華卡通台">
    <title>森林偵探</title>
    <desc></desc>
  </programme>
  <programme start="20260118110000 +0800" stop="20260118113000 +0800" channel="龍華卡通台">
    <title>呱張爆音團</title>
    <desc></desc>
  </programme>
  <programme start="20260118113000 +0800" stop="20260118120000 +0800" channel="龍華卡通台">
    <title>呱張爆音團</title>
    <desc></desc>
  </programme>
  <programme start="20260118120000 +0800" stop="20260118123000 +0800" channel="龍華卡通台">
    <title>呱張爆音團</title>
    <desc></desc>
  </programme>
  <programme start="20260118123000 +0800" stop="20260118130000 +0800" channel="龍華卡通台">
    <title>呱張爆音團</title>
    <desc></desc>
  </programme>
  <programme start="20260118130000 +0800" stop="20260118133000 +0800" channel="龍華卡通台">
    <title>南瓜入侵</title>
    <desc></desc>
  </programme>
  <programme start="20260118133000 +0800" stop="20260118140000 +0800" channel="龍華卡通台">
    <title>南瓜入侵</title>
    <desc></desc>
  </programme>
  <programme start="20260118140000 +0800" stop="20260118143000 +0800" channel="龍華卡通台">
    <title>豆小鴨</title>
    <desc></desc>
  </programme>
  <programme start="20260118143000 +0800" stop="20260118150000 +0800" channel="龍華卡通台">
    <title>豆小鴨</title>
    <desc></desc>
  </programme>
  <programme start="20260118150000 +0800" stop="20260118153000 +0800" channel="龍華卡通台">
    <title>呱張爆音團</title>
    <desc></desc>
  </programme>
  <programme start="20260118153000 +0800" stop="20260118160000 +0800" channel="龍華卡通台">
    <title>呱張爆音團</title>
    <desc></desc>
  </programme>
  <programme start="20260118160000 +0800" stop="20260118163000 +0800" channel="龍華卡通台">
    <title>呱張爆音團</title>
    <desc></desc>
  </programme>
  <programme start="20260118163000 +0800" stop="20260118170000 +0800" channel="龍華卡通台">
    <title>呱張爆音團</title>
    <desc></desc>
  </programme>
  <programme start="20260118170000 +0800" stop="20260118173000 +0800" channel="龍華卡通台">
    <title>豆小鴨</title>
    <desc></desc>
  </programme>
  <programme start="20260118173000 +0800" stop="20260118180000 +0800" channel="龍華卡通台">
    <title>豆小鴨</title>
    <desc></desc>
  </programme>
  <programme start="20260118180000 +0800" stop="20260118183000 +0800" channel="龍華卡通台">
    <title>森林偵探</title>
    <desc></desc>
  </programme>
  <programme start="20260118183000 +0800" stop="20260118190000 +0800" channel="龍華卡通台">
    <title>森林偵探</title>
    <desc></desc>
  </programme>
  <programme start="20260118190000 +0800" stop="20260118193000 +0800" channel="龍華卡通台">
    <title>呱張爆音團</title>
    <desc></desc>
  </programme>
  <programme start="20260118193000 +0800" stop="20260118200000 +0800" channel="龍華卡通台">
    <title>呱張爆音團</title>
    <desc></desc>
  </programme>
  <programme start="20260118200000 +0800" stop="20260118203000 +0800" channel="龍華卡通台">
    <title>呱張爆音團</title>
    <desc></desc>
  </programme>
  <programme start="20260118203000 +0800" stop="20260118210000 +0800" channel="龍華卡通台">
    <title>呱張爆音團</title>
    <desc></desc>
  </programme>
  <programme start="20260118210000 +0800" stop="20260118213000 +0800" channel="龍華卡通台">
    <title>南瓜入侵</title>
    <desc></desc>
  </programme>
  <programme start="20260118213000 +0800" stop="20260118220000 +0800" channel="龍華卡通台">
    <title>南瓜入侵</title>
    <desc></desc>
  </programme>
  <programme start="20260118220000 +0800" stop="20260118223000 +0800" channel="龍華卡通台">
    <title>豆小鴨</title>
    <desc></desc>
  </programme>
  <programme start="20260118223000 +0800" stop="20260118230000 +0800" channel="龍華卡通台">
    <title>豆小鴨</title>
    <desc></desc>
  </programme>
  <programme start="20260118230000 +0800" stop="20260118233000 +0800" channel="龍華卡通台">
    <title>森林偵探</title>
    <desc></desc>
  </programme>
  <programme start="20260118233000 +0800" stop="20260119000000 +0800" channel="龍華卡通台">
    <title>森林偵探</title>
    <desc></desc>
  </programme>
  <channel id="龍華日韓台">
    <display-name>龍華日韓台</display-name>
  </channel>
  <programme start="20260117220000 +0800" stop="20260118000000 +0800" channel="龍華日韓台">
    <title>好搭檔</title>
    <desc></desc>
  </programme>
  <programme start="20260118000000 +0800" stop="20260118030000 +0800" channel="龍華日韓台">
    <title>紳士與小姐</title>
    <desc></desc>
  </programme>
  <programme start="20260118030000 +0800" stop="20260118050000 +0800" channel="龍華日韓台">
    <title>好搭檔</title>
    <desc></desc>
  </programme>
  <programme start="20260118050000 +0800" stop="20260118070000 +0800" channel="龍華日韓台">
    <title>男朋友</title>
    <desc></desc>
  </programme>
  <programme start="20260118070000 +0800" stop="20260118100000 +0800" channel="龍華日韓台">
    <title>兩個女人的房間</title>
    <desc></desc>
  </programme>
  <programme start="20260118100000 +0800" stop="20260118120000 +0800" channel="龍華日韓台">
    <title>好搭檔</title>
    <desc></desc>
  </programme>
  <programme start="20260118120000 +0800" stop="20260118140000 +0800" channel="龍華日韓台">
    <title>男朋友</title>
    <desc></desc>
  </programme>
  <programme start="20260118140000 +0800" stop="20260118170000 +0800" channel="龍華日韓台">
    <title>紳士與小姐</title>
    <desc></desc>
  </programme>
  <programme start="20260118170000 +0800" stop="20260118200000 +0800" channel="龍華日韓台">
    <title>兩個女人的房間</title>
    <desc></desc>
  </programme>
  <programme start="20260118200000 +0800" stop="20260118220000 +0800" channel="龍華日韓台">
    <title>男朋友</title>
    <desc></desc>
  </programme>
  <programme start="20260118220000 +0800" stop="20260119000000 +0800" channel="龍華日韓台">
    <title>好搭檔</title>
    <desc></desc>
  </programme>
  <channel id="龍華偶像台">
    <display-name>龍華偶像台</display-name>
  </channel>
  <programme start="20260117220000 +0800" stop="20260118000000 +0800" channel="龍華偶像台">
    <title>時光之城</title>
    <desc></desc>
  </programme>
  <programme start="20260118000000 +0800" stop="20260118020000 +0800" channel="龍華偶像台">
    <title>奇蹟的兄弟</title>
    <desc></desc>
  </programme>
  <programme start="20260118020000 +0800" stop="20260118040000 +0800" channel="龍華偶像台">
    <title>向風而行</title>
    <desc></desc>
  </programme>
  <programme start="20260118040000 +0800" stop="20260118060000 +0800" channel="龍華偶像台">
    <title>時光之城</title>
    <desc></desc>
  </programme>
  <programme start="20260118060000 +0800" stop="20260118083000 +0800" channel="龍華偶像台">
    <title>愛情是Beautiful，人生是Wonderful</title>
    <desc></desc>
  </programme>
  <programme start="20260118083000 +0800" stop="20260118100000 +0800" channel="龍華偶像台">
    <title>韶華若錦</title>
    <desc></desc>
  </programme>
  <programme start="20260118100000 +0800" stop="20260118120000 +0800" channel="龍華偶像台">
    <title>時光之城</title>
    <desc></desc>
  </programme>
  <programme start="20260118120000 +0800" stop="20260118140000 +0800" channel="龍華偶像台">
    <title>奇蹟的兄弟</title>
    <desc></desc>
  </programme>
  <programme start="20260118140000 +0800" stop="20260118160000 +0800" channel="龍華偶像台">
    <title>向風而行</title>
    <desc></desc>
  </programme>
  <programme start="20260118160000 +0800" stop="20260118173000 +0800" channel="龍華偶像台">
    <title>韶華若錦</title>
    <desc></desc>
  </programme>
  <programme start="20260118173000 +0800" stop="20260118203000 +0800" channel="龍華偶像台">
    <title>愛情是Beautiful，人生是Wonderful</title>
    <desc></desc>
  </programme>
  <programme start="20260118203000 +0800" stop="20260118220000 +0800" channel="龍華偶像台">
    <title>韶華若錦</title>
    <desc></desc>
  </programme>
  <programme start="20260118220000 +0800" stop="20260119000000 +0800" channel="龍華偶像台">
    <title>時光之城</title>
    <desc></desc>
  </programme>
  <channel id="LS-Time電影台">
    <display-name>LS-Time電影台</display-name>
  </channel>
  <programme start="20260118000000 +0800" stop="20260118020500 +0800" channel="LS-Time電影台">
    <title>無節目資料</title>
    <desc></desc>
  </programme>
  <programme start="20260118020500 +0800" stop="20260118042500 +0800" channel="LS-Time電影台">
    <title>火燒紅蓮寺</title>
    <desc></desc>
  </programme>
  <programme start="20260118021500 +0800" stop="20260118042500 +0800" channel="LS-Time電影台">
    <title>真心英雄</title>
    <desc></desc>
  </programme>
  <programme start="20260118042500 +0800" stop="20260118064500 +0800" channel="LS-Time電影台">
    <title>整人專家</title>
    <desc></desc>
  </programme>
  <programme start="20260118064500 +0800" stop="20260118091000 +0800" channel="LS-Time電影台">
    <title>喋血雙雄</title>
    <desc></desc>
  </programme>
  <programme start="20260118091000 +0800" stop="20260118113500 +0800" channel="LS-Time電影台">
    <title>九品芝麻官</title>
    <desc></desc>
  </programme>
  <programme start="20260118113500 +0800" stop="20260118135500 +0800" channel="LS-Time電影台">
    <title>特務迷城</title>
    <desc></desc>
  </programme>
  <programme start="20260118135500 +0800" stop="20260118164500 +0800" channel="LS-Time電影台">
    <title>出神入化2</title>
    <desc></desc>
  </programme>
  <programme start="20260118164500 +0800" stop="20260118190000 +0800" channel="LS-Time電影台">
    <title>威龍闖天關</title>
    <desc></desc>
  </programme>
  <programme start="20260118190000 +0800" stop="20260118210000 +0800" channel="LS-Time電影台">
    <title>警慌失措</title>
    <desc></desc>
  </programme>
  <programme start="20260118210000 +0800" stop="20260118233000 +0800" channel="LS-Time電影台">
    <title>無價之保</title>
    <desc></desc>
  </programme>
  <programme start="20260118225500 +0800" stop="20260119000000 +0800" channel="LS-Time電影台">
    <title>投名狀</title>
    <desc></desc>
  </programme>
  <programme start="20260118234000 +0800" stop="20260119000000 +0800" channel="LS-Time電影台">
    <title>凶貓</title>
    <desc></desc>
  </programme>
  <programme start="20260119000000 +0800" stop="20260119014000 +0800" channel="LS-Time電影台">
    <title>投名狀</title>
    <desc></desc>
  </programme>
  <programme start="20260119000000 +0800" stop="20260119013000 +0800" channel="LS-Time電影台">
    <title>凶貓</title>
    <desc></desc>
  </programme>
  <programme start="20260119013500 +0800" stop="20260119040000 +0800" channel="LS-Time電影台">
    <title>四大探長</title>
    <desc></desc>
  </programme>
  <programme start="20260119013500 +0800" stop="20260119043000 +0800" channel="LS-Time電影台">
    <title>大上海</title>
    <desc></desc>
  </programme>
  <programme start="20260119040000 +0800" stop="20260119060500 +0800" channel="LS-Time電影台">
    <title>小蝦米對大鯨魚3直擊證人</title>
    <desc></desc>
  </programme>
  <programme start="20260119043000 +0800" stop="20260119063000 +0800" channel="LS-Time電影台">
    <title>汽水炸彈</title>
    <desc></desc>
  </programme>
  <programme start="20260119060500 +0800" stop="20260119080500 +0800" channel="LS-Time電影台">
    <title>表哥你好</title>
    <desc></desc>
  </programme>
  <programme start="20260119063000 +0800" stop="20260119090000 +0800" channel="LS-Time電影台">
    <title>黃飛鴻之鐵雞鬥蜈蚣</title>
    <desc></desc>
  </programme>
  <programme start="20260119080500 +0800" stop="20260119110000 +0800" channel="LS-Time電影台">
    <title>我是路人甲</title>
    <desc></desc>
  </programme>
  <programme start="20260119090000 +0800" stop="20260119110500 +0800" channel="LS-Time電影台">
    <title>群龍戲鳳</title>
    <desc></desc>
  </programme>
  <programme start="20260119110000 +0800" stop="20260119131000 +0800" channel="LS-Time電影台">
    <title>俠盜高飛</title>
    <desc></desc>
  </programme>
  <programme start="20260119110500 +0800" stop="20260119133500 +0800" channel="LS-Time電影台">
    <title>錦衣衛</title>
    <desc></desc>
  </programme>
  <programme start="20260119131000 +0800" stop="20260119154500 +0800" channel="LS-Time電影台">
    <title>八百壯士</title>
    <desc></desc>
  </programme>
  <programme start="20260119133500 +0800" stop="20260119160000 +0800" channel="LS-Time電影台">
    <title>四大探長</title>
    <desc></desc>
  </programme>
  <programme start="20260119154500 +0800" stop="20260119182000 +0800" channel="LS-Time電影台">
    <title>無家可歸的中學生</title>
    <desc></desc>
  </programme>
  <programme start="20260119160000 +0800" stop="20260119180500 +0800" channel="LS-Time電影台">
    <title>倩女幽魂</title>
    <desc></desc>
  </programme>
  <programme start="20260119180500 +0800" stop="20260119210000 +0800" channel="LS-Time電影台">
    <title>盲探</title>
    <desc></desc>
  </programme>
  <programme start="20260119182000 +0800" stop="20260119210000 +0800" channel="LS-Time電影台">
    <title>騙神！騙鬼！金先達</title>
    <desc></desc>
  </programme>
  <programme start="20260119210000 +0800" stop="20260119225500 +0800" channel="LS-Time電影台">
    <title>無界限</title>
    <desc></desc>
  </programme>
  <programme start="20260119210000 +0800" stop="20260119234000 +0800" channel="LS-Time電影台">
    <title>赤道</title>
    <desc></desc>
  </programme>
  <programme start="20260119233500 +0800" stop="20260120000000 +0800" channel="LS-Time電影台">
    <title>計程車屠夫</title>
    <desc></desc>
  </programme>
  <programme start="20260120000000 +0800" stop="20260120013000 +0800" channel="LS-Time電影台">
    <title>計程車屠夫</title>
    <desc></desc>
  </programme>
  <programme start="20260120014000 +0800" stop="20260120043000 +0800" channel="LS-Time電影台">
    <title>遊戲規則</title>
    <desc></desc>
  </programme>
  <programme start="20260120043000 +0800" stop="20260120064500 +0800" channel="LS-Time電影台">
    <title>神算鯊鯊鯊</title>
    <desc></desc>
  </programme>
  <programme start="20260120064500 +0800" stop="20260120085000 +0800" channel="LS-Time電影台">
    <title>風雨操場</title>
    <desc></desc>
  </programme>
  <programme start="20260120085000 +0800" stop="20260120112000 +0800" channel="LS-Time電影台">
    <title>這個殺手演很大</title>
    <desc></desc>
  </programme>
  <programme start="20260120112000 +0800" stop="20260120135000 +0800" channel="LS-Time電影台">
    <title>我在死牢的日子</title>
    <desc></desc>
  </programme>
  <programme start="20260120135000 +0800" stop="20260120163500 +0800" channel="LS-Time電影台">
    <title>至尊無上</title>
    <desc></desc>
  </programme>
  <programme start="20260120163500 +0800" stop="20260120185000 +0800" channel="LS-Time電影台">
    <title>搶錢夫妻</title>
    <desc></desc>
  </programme>
  <programme start="20260120185000 +0800" stop="20260120210000 +0800" channel="LS-Time電影台">
    <title>通天大盜</title>
    <desc></desc>
  </programme>
  <programme start="20260120210000 +0800" stop="20260120233500 +0800" channel="LS-Time電影台">
    <title>富都青年</title>
    <desc></desc>
  </programme>
  <programme start="20260120232500 +0800" stop="20260121000000 +0800" channel="LS-Time電影台">
    <title>龍門飛甲</title>
    <desc></desc>
  </programme>
  <programme start="20260121000000 +0800" stop="20260121021000 +0800" channel="LS-Time電影台">
    <title>龍門飛甲</title>
    <desc></desc>
  </programme>
  <programme start="20260121000000 +0800" stop="20260121013000 +0800" channel="LS-Time電影台">
    <title>無節目資料</title>
    <desc></desc>
  </programme>
  <programme start="20260121013000 +0800" stop="20260121033000 +0800" channel="LS-Time電影台">
    <title>吉祥酒店</title>
    <desc></desc>
  </programme>
  <programme start="20260121033000 +0800" stop="20260121052500 +0800" channel="LS-Time電影台">
    <title>烈火街頭</title>
    <desc></desc>
  </programme>
  <programme start="20260121052500 +0800" stop="20260121073000 +0800" channel="LS-Time電影台">
    <title>汽水炸彈</title>
    <desc></desc>
  </programme>
  <programme start="20260121073000 +0800" stop="20260121095500 +0800" channel="LS-Time電影台">
    <title>黃飛鴻之鐵雞鬥蜈蚣</title>
    <desc></desc>
  </programme>
  <programme start="20260121095500 +0800" stop="20260121121000 +0800" channel="LS-Time電影台">
    <title>最佳拍檔大顯神通</title>
    <desc></desc>
  </programme>
  <programme start="20260121121000 +0800" stop="20260121140000 +0800" channel="LS-Time電影台">
    <title>國產凌凌漆</title>
    <desc></desc>
  </programme>
  <programme start="20260121140000 +0800" stop="20260121164000 +0800" channel="LS-Time電影台">
    <title>告別單身</title>
    <desc></desc>
  </programme>
  <programme start="20260121164000 +0800" stop="20260121185000 +0800" channel="LS-Time電影台">
    <title>最佳拍檔女皇密令</title>
    <desc></desc>
  </programme>
  <programme start="20260121185000 +0800" stop="20260121210000 +0800" channel="LS-Time電影台">
    <title>風雨同路</title>
    <desc></desc>
  </programme>
  <programme start="20260121210000 +0800" stop="20260121232500 +0800" channel="LS-Time電影台">
    <title>無價之保</title>
    <desc></desc>
  </programme>
  <programme start="20260121231500 +0800" stop="20260122000000 +0800" channel="LS-Time電影台">
    <title>風水</title>
    <desc></desc>
  </programme>
  <programme start="20260122000000 +0800" stop="20260122020000 +0800" channel="LS-Time電影台">
    <title>風水</title>
    <desc></desc>
  </programme>
  <programme start="20260122021000 +0800" stop="20260122042500 +0800" channel="LS-Time電影台">
    <title>歡樂時光</title>
    <desc></desc>
  </programme>
  <programme start="20260122042500 +0800" stop="20260122064000 +0800" channel="LS-Time電影台">
    <title>等待黎明</title>
    <desc></desc>
  </programme>
  <programme start="20260122064000 +0800" stop="20260122085000 +0800" channel="LS-Time電影台">
    <title>水滸傳之英雄本色</title>
    <desc></desc>
  </programme>
  <programme start="20260122085000 +0800" stop="20260122105000 +0800" channel="LS-Time電影台">
    <title>八星報喜</title>
    <desc></desc>
  </programme>
  <programme start="20260122105000 +0800" stop="20260122125500 +0800" channel="LS-Time電影台">
    <title>倩女幽魂</title>
    <desc></desc>
  </programme>
  <programme start="20260122125500 +0800" stop="20260122150000 +0800" channel="LS-Time電影台">
    <title>藍色霹靂火</title>
    <desc></desc>
  </programme>
  <programme start="20260122150000 +0800" stop="20260122165500 +0800" channel="LS-Time電影台">
    <title>找錯對象投錯胎</title>
    <desc></desc>
  </programme>
  <programme start="20260122165500 +0800" stop="20260122185500 +0800" channel="LS-Time電影台">
    <title>小生怕怕</title>
    <desc></desc>
  </programme>
  <programme start="20260122185500 +0800" stop="20260122210000 +0800" channel="LS-Time電影台">
    <title>丐世英雄</title>
    <desc></desc>
  </programme>
  <programme start="20260122210000 +0800" stop="20260122231500 +0800" channel="LS-Time電影台">
    <title>夏洛特煩惱</title>
    <desc></desc>
  </programme>
  <programme start="20260122230500 +0800" stop="20260123000000 +0800" channel="LS-Time電影台">
    <title>出神入化2</title>
    <desc></desc>
  </programme>
  <programme start="20260123000000 +0800" stop="20260123020000 +0800" channel="LS-Time電影台">
    <title>出神入化2</title>
    <desc></desc>
  </programme>
  <programme start="20260123020000 +0800" stop="20260123041500 +0800" channel="LS-Time電影台">
    <title>水雞鬥老虎</title>
    <desc></desc>
  </programme>
  <programme start="20260123041500 +0800" stop="20260123063000 +0800" channel="LS-Time電影台">
    <title>新英雄本色</title>
    <desc></desc>
  </programme>
  <programme start="20260123063000 +0800" stop="20260123084500 +0800" channel="LS-Time電影台">
    <title>江湖情</title>
    <desc></desc>
  </programme>
  <programme start="20260123084500 +0800" stop="20260123105500 +0800" channel="LS-Time電影台">
    <title>我在黑社會的日子</title>
    <desc></desc>
  </programme>
  <programme start="20260123105500 +0800" stop="20260123131000 +0800" channel="LS-Time電影台">
    <title>倩女幽魂2人間道</title>
    <desc></desc>
  </programme>
  <programme start="20260123131000 +0800" stop="20260123152500 +0800" channel="LS-Time電影台">
    <title>鐵甲無敵瑪利亞</title>
    <desc></desc>
  </programme>
  <programme start="20260123152500 +0800" stop="20260123180500 +0800" channel="LS-Time電影台">
    <title>非誠勿擾</title>
    <desc></desc>
  </programme>
  <programme start="20260123180500 +0800" stop="20260123210000 +0800" channel="LS-Time電影台">
    <title>明月幾時有</title>
    <desc></desc>
  </programme>
  <programme start="20260123210000 +0800" stop="20260123230500 +0800" channel="LS-Time電影台">
    <title>報告班長2</title>
    <desc></desc>
  </programme>
  <programme start="20260123232000 +0800" stop="20260124000000 +0800" channel="LS-Time電影台">
    <title>來自雪國的遺書</title>
    <desc></desc>
  </programme>
  <programme start="20260124000000 +0800" stop="20260124022000 +0800" channel="LS-Time電影台">
    <title>來自雪國的遺書</title>
    <desc></desc>
  </programme>
  <programme start="20260124000000 +0800" stop="20260124020000 +0800" channel="LS-Time電影台">
    <title>無節目資料</title>
    <desc></desc>
  </programme>
  <programme start="20260124020000 +0800" stop="20260124035500 +0800" channel="LS-Time電影台">
    <title>再世豪哥</title>
    <desc></desc>
  </programme>
  <programme start="20260124035500 +0800" stop="20260124054500 +0800" channel="LS-Time電影台">
    <title>險角</title>
    <desc></desc>
  </programme>
  <programme start="20260124054500 +0800" stop="20260124074000 +0800" channel="LS-Time電影台">
    <title>龍在江湖</title>
    <desc></desc>
  </programme>
  <programme start="20260124074000 +0800" stop="20260124093500 +0800" channel="LS-Time電影台">
    <title>開心鬼撞鬼</title>
    <desc></desc>
  </programme>
  <programme start="20260124093500 +0800" stop="20260124120500 +0800" channel="LS-Time電影台">
    <title>倩女幽魂3道道道</title>
    <desc></desc>
  </programme>
  <programme start="20260124120500 +0800" stop="20260124140500 +0800" channel="LS-Time電影台">
    <title>醉拳3</title>
    <desc></desc>
  </programme>
  <programme start="20260124140500 +0800" stop="20260124161000 +0800" channel="LS-Time電影台">
    <title>圓明園</title>
    <desc></desc>
  </programme>
  <programme start="20260124161000 +0800" stop="20260124183000 +0800" channel="LS-Time電影台">
    <title>英雄會少林</title>
    <desc></desc>
  </programme>
  <programme start="20260124183000 +0800" stop="20260124210000 +0800" channel="LS-Time電影台">
    <title>無價之保</title>
    <desc></desc>
  </programme>
  <programme start="20260124210000 +0800" stop="20260124232000 +0800" channel="LS-Time電影台">
    <title>噪反</title>
    <desc></desc>
  </programme>
  <channel id="天映頻道">
    <display-name>天映頻道</display-name>
  </channel>
  <programme start="20260118000000 +0800" stop="20260118014600 +0800" channel="天映頻道">
    <title>無節目資料</title>
    <desc></desc>
  </programme>
  <programme start="20260118014600 +0800" stop="20260118031400 +0800" channel="天映頻道">
    <title>City of Desire</title>
    <desc>Sister 13 returns to Macau after 17 years to succeed her father’s underground empire, the prostitution business. She tries to stop their exploitation of the sex workers, but Macau’s economy flourished after the handover, propelling the prostitution and gambling businesses. The city is blinded by desire and Sister 13 can do nothing to help…</desc>
  </programme>
  <programme start="20260118031400 +0800" stop="20260118045300 +0800" channel="天映頻道">
    <title>Mr &amp; Mrs Gambler</title>
    <desc>Manfred and Flora are gambling addicts who have come across each other a few times at the casino, but do not leave impression on each other until they both suffer heavy losses and are held hostage by the loan sharks in Macau. They find themselves falling in love, and decide to get married when they come back to Hong Kong.</desc>
  </programme>
  <programme start="20260118045300 +0800" stop="20260118064600 +0800" channel="天映頻道">
    <title>Cyber Heist</title>
    <desc>Hackers have caused a large-scale cyber attack, but luckily cyber security engineer Chun, manages to fend it off with his protective firewall system. To Chun's surprise, his boss is the mastermind of the attack, and when Chun gets trapped in a money laundering operation, he must fight against his boss in the cyber world to prove his innocence.</desc>
  </programme>
  <programme start="20260118064600 +0800" stop="20260118082300 +0800" channel="天映頻道">
    <title>Tales from the Occult: Body and Soul</title>
    <desc>This horror anthology series returns to feature three spooky crime stories about an ex-hair model, a cat lover and the love triangle between a dental nurse, a dentist and a chef. The stories depict their paths from obsession to madness, eventually tipping them over to the dark side of human nature.</desc>
  </programme>
  <programme start="20260118082300 +0800" stop="20260118101100 +0800" channel="天映頻道">
    <title>The Hedgehog</title>
    <desc>Wang's odd behaviour and quirky ideas make him a social outcast. His teenage nephew Zhou, who is ashamed of his stutter, becomes Wang's only friend. Together, these misfits challenge traditional family expectations and social misunderstandings, supporting and inspiring each other as they seek their own paths in life.</desc>
  </programme>
  <programme start="20260118101100 +0800" stop="20260118115100 +0800" channel="天映頻道">
    <title>Treasure Hunt</title>
    <desc>A commercial director Peggy shoots an ad on a deserted island while some mysterious men with the treasure map are also there to hunt for the hidden Ming Dynasty treasures. However, the map is stolen by Star who lives on the island. Star and Peggy unveil the hidden treasures but end up being chased by the mysterious men…</desc>
  </programme>
  <programme start="20260118115100 +0800" stop="20260118133300 +0800" channel="天映頻道">
    <title>Young and Dangerous: Reloaded</title>
    <desc>In this remake of “Young and Dangerous”, Chan Ho Nam and his three buddies of the Hung Hing triad gang strive to fight for their own justice, further expanding their power in the triad and becoming a new legend...</desc>
  </programme>
  <programme start="20260118133300 +0800" stop="20260118150800 +0800" channel="天映頻道">
    <title>Lonely Eighteen</title>
    <desc>Set in the 1980s Hong Kong, Elaine and her best friend Ying enter the entertainment industry hoping to change their fates from poverty. Ying soon becomes a popular porn star but Elaine is lost between being her true self and an actress. When show business declines after a decade, their choices lead them to two different paths in life.</desc>
  </programme>
  <programme start="20260118150800 +0800" stop="20260118163700 +0800" channel="天映頻道">
    <title>Love and Let Love!</title>
    <desc>Cliff proposes to his girlfriend Terry but is killed in a car accident before she says “yes”. Terry is devastated and inconsolable. When Cliff's ghost returns, they seem to go back to their good old days. However, Cliff is determined to help Terry get over his death and start anew.</desc>
  </programme>
  <programme start="20260118163700 +0800" stop="20260118181400 +0800" channel="天映頻道">
    <title>Little Red Sweet</title>
    <desc>A Chinese dessert shop owned by the Chang family in Kowloon City faces upheaval when the mother suffers a devastating stroke. Their daughter sacrifices her dream of becoming a flight attendant to help keep the family business alive, but tensions rise as she clashes with her father. Can they find a way to overcome their struggles and remain united?</desc>
  </programme>
  <programme start="20260118181400 +0800" stop="20260118194500 +0800" channel="天映頻道">
    <title>My Kung Fu Sweetheart</title>
    <desc>Phoenix’s (Cecilia Cheung) parents are martial arts superheroes, who hide their true identities while ferreting out evil martial artists. Phoenix gets the go-ahead to train in the misty mountains, where she learns of her all-important romantic destiny...</desc>
  </programme>
  <programme start="20260118194500 +0800" stop="20260118220000 +0800" channel="天映頻道">
    <title>Moscow Mission</title>
    <desc>The story is based on a 1993 true event, the "China-Russia Train Robbery" where a gang of criminals commits a heist, stealing cash and goods from the cross border train. A Chinese police officer disguises as a businessman heads the operation to arrest the criminals, but uncovers a bigger conspiracy instead…</desc>
  </programme>
  <programme start="20260118220000 +0800" stop="20260118234300 +0800" channel="天映頻道">
    <title>The Sorcerer &amp; The White Snake</title>
    <desc>In this action fantasy movie based on the Chinese legend of the White Snake, a young herbalist falls in love with a thousand-year-old white snake disguised as a woman. When the white snake's true identity is revealed, a sorcerer goes to battle believing that in doing so, he is restoring balance and order between man and the supernatural.</desc>
  </programme>
  <programme start="20260118234300 +0800" stop="20260119000000 +0800" channel="天映頻道">
    <title>Coffin Homes</title>
    <desc>Three bizarre tales intertwine in this horror satire set against the housing crisis of Hong Kong, where soaring property prices have driven dwellers to take every insane effort necessary to secure a cramped space, even if it means sharing the same roof with the dead!</desc>
  </programme>
  <programme start="20260119000000 +0800" stop="20260119024300 +0800" channel="天映頻道">
    <title>Coffin Homes</title>
    <desc>Three bizarre tales intertwine in this horror satire set against the housing crisis of Hong Kong, where soaring property prices have driven dwellers to take every insane effort necessary to secure a cramped space, even if it means sharing the same roof with the dead!</desc>
  </programme>
</tv>