<?xml version='1.0' encoding='utf-8'?>
<tv>
  <channel id="LS-Time電影台">
    <display-name>LS-Time電影台</display-name>
  </channel>
  <programme start="20260629000000 +0800" stop="20260629013000 +0800" channel="LS-Time電影台">
    <title>無節目資料</title>
    <desc></desc>
  </programme>
  <programme start="20260629013000 +0800" stop="20260629034000 +0800" channel="LS-Time電影台">
    <title>倩女幽魂</title>
    <desc></desc>
  </programme>
  <programme start="20260629013000 +0800" stop="20260629054000 +0800" channel="LS-Time電影台">
    <title>俠盜高飛</title>
    <desc></desc>
  </programme>
  <programme start="20260629034000 +0800" stop="20260629062500 +0800" channel="LS-Time電影台">
    <title>夜宴</title>
    <desc></desc>
  </programme>
  <programme start="20260629054000 +0800" stop="20260629075000 +0800" channel="LS-Time電影台">
    <title>賊美人</title>
    <desc></desc>
  </programme>
  <programme start="20260629062500 +0800" stop="20260629085500 +0800" channel="LS-Time電影台">
    <title>天下無賊</title>
    <desc></desc>
  </programme>
  <programme start="20260629075000 +0800" stop="20260629100000 +0800" channel="LS-Time電影台">
    <title>霹靂大神探</title>
    <desc></desc>
  </programme>
  <programme start="20260629085500 +0800" stop="20260629111500 +0800" channel="LS-Time電影台">
    <title>我老婆係明星</title>
    <desc></desc>
  </programme>
  <programme start="20260629100000 +0800" stop="20260629121500 +0800" channel="LS-Time電影台">
    <title>電車男</title>
    <desc></desc>
  </programme>
  <programme start="20260629111500 +0800" stop="20260629134000 +0800" channel="LS-Time電影台">
    <title>運財五福星</title>
    <desc></desc>
  </programme>
  <programme start="20260629121500 +0800" stop="20260629141500 +0800" channel="LS-Time電影台">
    <title>超強颱風</title>
    <desc></desc>
  </programme>
  <programme start="20260629134000 +0800" stop="20260629160000 +0800" channel="LS-Time電影台">
    <title>倚天屠龍記之魔教教主</title>
    <desc></desc>
  </programme>
  <programme start="20260629141500 +0800" stop="20260629163000 +0800" channel="LS-Time電影台">
    <title>逃學威龍</title>
    <desc></desc>
  </programme>
  <programme start="20260629160000 +0800" stop="20260629184500 +0800" channel="LS-Time電影台">
    <title>我的野蠻女友2-蠻風再現</title>
    <desc></desc>
  </programme>
  <programme start="20260629163000 +0800" stop="20260629184000 +0800" channel="LS-Time電影台">
    <title>最佳損友闖情關</title>
    <desc></desc>
  </programme>
  <programme start="20260629184000 +0800" stop="20260629210000 +0800" channel="LS-Time電影台">
    <title>倚天屠龍記之魔教教主</title>
    <desc></desc>
  </programme>
  <programme start="20260629184500 +0800" stop="20260629210000 +0800" channel="LS-Time電影台">
    <title>咖喱辣椒</title>
    <desc></desc>
  </programme>
  <programme start="20260629210000 +0800" stop="20260629233000 +0800" channel="LS-Time電影台">
    <title>綫人</title>
    <desc></desc>
  </programme>
  <programme start="20260629210000 +0800" stop="20260629235000 +0800" channel="LS-Time電影台">
    <title>遊戲規則</title>
    <desc></desc>
  </programme>
  <programme start="20260629230500 +0800" stop="20260630000000 +0800" channel="LS-Time電影台">
    <title>竊聽風雲</title>
    <desc></desc>
  </programme>
  <programme start="20260629234000 +0800" stop="20260630000000 +0800" channel="LS-Time電影台">
    <title>G4特工</title>
    <desc></desc>
  </programme>
  <programme start="20260630000000 +0800" stop="20260630011500 +0800" channel="LS-Time電影台">
    <title>竊聽風雲</title>
    <desc></desc>
  </programme>
  <programme start="20260630000000 +0800" stop="20260630020500 +0800" channel="LS-Time電影台">
    <title>G4特工</title>
    <desc></desc>
  </programme>
  <programme start="20260630000000 +0800" stop="20260630012500 +0800" channel="LS-Time電影台">
    <title>無節目資料</title>
    <desc></desc>
  </programme>
  <programme start="20260630012500 +0800" stop="20260630035000 +0800" channel="LS-Time電影台">
    <title>喋血雙雄</title>
    <desc></desc>
  </programme>
  <programme start="20260630021500 +0800" stop="20260630050500 +0800" channel="LS-Time電影台">
    <title>黃泉路</title>
    <desc></desc>
  </programme>
  <programme start="20260630035000 +0800" stop="20260630063000 +0800" channel="LS-Time電影台">
    <title>神話</title>
    <desc></desc>
  </programme>
  <programme start="20260630050500 +0800" stop="20260630070000 +0800" channel="LS-Time電影台">
    <title>刀劍笑</title>
    <desc></desc>
  </programme>
  <programme start="20260630063000 +0800" stop="20260630085000 +0800" channel="LS-Time電影台">
    <title>玩命KO-曼谷重擊</title>
    <desc></desc>
  </programme>
  <programme start="20260630070000 +0800" stop="20260630085500 +0800" channel="LS-Time電影台">
    <title>大丈夫日記</title>
    <desc></desc>
  </programme>
  <programme start="20260630085000 +0800" stop="20260630110000 +0800" channel="LS-Time電影台">
    <title>鬼咬鬼</title>
    <desc></desc>
  </programme>
  <programme start="20260630085500 +0800" stop="20260630112000 +0800" channel="LS-Time電影台">
    <title>三少爺的劍</title>
    <desc></desc>
  </programme>
  <programme start="20260630110000 +0800" stop="20260630133500 +0800" channel="LS-Time電影台">
    <title>功夫棒球</title>
    <desc></desc>
  </programme>
  <programme start="20260630112000 +0800" stop="20260630135500 +0800" channel="LS-Time電影台">
    <title>中華英雄</title>
    <desc></desc>
  </programme>
  <programme start="20260630133500 +0800" stop="20260630162500 +0800" channel="LS-Time電影台">
    <title>鎗神</title>
    <desc></desc>
  </programme>
  <programme start="20260630135500 +0800" stop="20260630155500 +0800" channel="LS-Time電影台">
    <title>富貴再逼人</title>
    <desc></desc>
  </programme>
  <programme start="20260630155500 +0800" stop="20260630184000 +0800" channel="LS-Time電影台">
    <title>至尊無上</title>
    <desc></desc>
  </programme>
  <programme start="20260630162500 +0800" stop="20260630183500 +0800" channel="LS-Time電影台">
    <title>流氓醫生</title>
    <desc></desc>
  </programme>
  <programme start="20260630183500 +0800" stop="20260630210000 +0800" channel="LS-Time電影台">
    <title>三少爺的劍</title>
    <desc></desc>
  </programme>
  <programme start="20260630184000 +0800" stop="20260630210000 +0800" channel="LS-Time電影台">
    <title>娘砲足球隊</title>
    <desc></desc>
  </programme>
  <programme start="20260630210000 +0800" stop="20260630234000 +0800" channel="LS-Time電影台">
    <title>電影版 嬌妻出沒注意</title>
    <desc></desc>
  </programme>
  <programme start="20260630210000 +0800" stop="20260630230500 +0800" channel="LS-Time電影台">
    <title>報告班長2</title>
    <desc></desc>
  </programme>
  <programme start="20260630231500 +0800" stop="20260701000000 +0800" channel="LS-Time電影台">
    <title>火龍</title>
    <desc></desc>
  </programme>
  <programme start="20260701000000 +0800" stop="20260701013500 +0800" channel="LS-Time電影台">
    <title>火龍</title>
    <desc></desc>
  </programme>
  <programme start="20260701020500 +0800" stop="20260701040500 +0800" channel="LS-Time電影台">
    <title>新唐山大兄</title>
    <desc></desc>
  </programme>
  <programme start="20260701040500 +0800" stop="20260701063000 +0800" channel="LS-Time電影台">
    <title>再見瓦城</title>
    <desc></desc>
  </programme>
  <programme start="20260701063000 +0800" stop="20260701091000 +0800" channel="LS-Time電影台">
    <title>英雄本色3</title>
    <desc></desc>
  </programme>
  <programme start="20260701091000 +0800" stop="20260701111000 +0800" channel="LS-Time電影台">
    <title>大搜查之女</title>
    <desc></desc>
  </programme>
  <programme start="20260701111000 +0800" stop="20260701135000 +0800" channel="LS-Time電影台">
    <title>戰鼓</title>
    <desc></desc>
  </programme>
  <programme start="20260701135000 +0800" stop="20260701164500 +0800" channel="LS-Time電影台">
    <title>三城記</title>
    <desc></desc>
  </programme>
  <programme start="20260701164500 +0800" stop="20260701184500 +0800" channel="LS-Time電影台">
    <title>富貴再逼人</title>
    <desc></desc>
  </programme>
  <programme start="20260701184500 +0800" stop="20260701210000 +0800" channel="LS-Time電影台">
    <title>橫掃天下</title>
    <desc></desc>
  </programme>
  <programme start="20260701210000 +0800" stop="20260701231500 +0800" channel="LS-Time電影台">
    <title>海峽兩岸</title>
    <desc></desc>
  </programme>
  <programme start="20260701233500 +0800" stop="20260702000000 +0800" channel="LS-Time電影台">
    <title>陰果</title>
    <desc></desc>
  </programme>
  <programme start="20260702000000 +0800" stop="20260702013000 +0800" channel="LS-Time電影台">
    <title>陰果</title>
    <desc></desc>
  </programme>
  <programme start="20260702000000 +0800" stop="20260702013500 +0800" channel="LS-Time電影台">
    <title>無節目資料</title>
    <desc></desc>
  </programme>
  <programme start="20260702013500 +0800" stop="20260702032500 +0800" channel="LS-Time電影台">
    <title>天羅地網</title>
    <desc></desc>
  </programme>
  <programme start="20260702032500 +0800" stop="20260702053500 +0800" channel="LS-Time電影台">
    <title>非常愛情</title>
    <desc></desc>
  </programme>
  <programme start="20260702053500 +0800" stop="20260702073000 +0800" channel="LS-Time電影台">
    <title>白色酢漿草</title>
    <desc></desc>
  </programme>
  <programme start="20260702073000 +0800" stop="20260702103000 +0800" channel="LS-Time電影台">
    <title>死亡預告</title>
    <desc></desc>
  </programme>
  <programme start="20260702103000 +0800" stop="20260702132000 +0800" channel="LS-Time電影台">
    <title>五億探長雷洛傳</title>
    <desc></desc>
  </programme>
  <programme start="20260702132000 +0800" stop="20260702160000 +0800" channel="LS-Time電影台">
    <title>集結號</title>
    <desc></desc>
  </programme>
  <programme start="20260702160000 +0800" stop="20260702182500 +0800" channel="LS-Time電影台">
    <title>賭俠</title>
    <desc></desc>
  </programme>
  <programme start="20260702182500 +0800" stop="20260702210000 +0800" channel="LS-Time電影台">
    <title>賭俠2之上海灘賭聖</title>
    <desc></desc>
  </programme>
  <programme start="20260702210000 +0800" stop="20260702233500 +0800" channel="LS-Time電影台">
    <title>花木蘭</title>
    <desc></desc>
  </programme>
  <programme start="20260702231000 +0800" stop="20260703000000 +0800" channel="LS-Time電影台">
    <title>鬼巴士</title>
    <desc></desc>
  </programme>
  <programme start="20260703000000 +0800" stop="20260703011000 +0800" channel="LS-Time電影台">
    <title>鬼巴士</title>
    <desc></desc>
  </programme>
  <programme start="20260703000000 +0800" stop="20260703013000 +0800" channel="LS-Time電影台">
    <title>無節目資料</title>
    <desc></desc>
  </programme>
  <programme start="20260703013000 +0800" stop="20260703042000 +0800" channel="LS-Time電影台">
    <title>黃泉路</title>
    <desc></desc>
  </programme>
  <programme start="20260703042000 +0800" stop="20260703064000 +0800" channel="LS-Time電影台">
    <title>魔幻廚房</title>
    <desc></desc>
  </programme>
  <programme start="20260703064000 +0800" stop="20260703091000 +0800" channel="LS-Time電影台">
    <title>跳水男孩</title>
    <desc></desc>
  </programme>
  <programme start="20260703091000 +0800" stop="20260703112000 +0800" channel="LS-Time電影台">
    <title>最佳損友闖情關</title>
    <desc></desc>
  </programme>
  <programme start="20260703112000 +0800" stop="20260703134500 +0800" channel="LS-Time電影台">
    <title>火龍</title>
    <desc></desc>
  </programme>
  <programme start="20260703134500 +0800" stop="20260703160500 +0800" channel="LS-Time電影台">
    <title>玩命KO-曼谷重擊</title>
    <desc></desc>
  </programme>
  <programme start="20260703160500 +0800" stop="20260703181000 +0800" channel="LS-Time電影台">
    <title>大佬愛美麗</title>
    <desc></desc>
  </programme>
  <programme start="20260703181000 +0800" stop="20260703210000 +0800" channel="LS-Time電影台">
    <title>風水</title>
    <desc></desc>
  </programme>
  <programme start="20260703210000 +0800" stop="20260703231000 +0800" channel="LS-Time電影台">
    <title>鬼咬鬼</title>
    <desc></desc>
  </programme>
  <programme start="20260703234000 +0800" stop="20260704000000 +0800" channel="LS-Time電影台">
    <title>父女變錯身</title>
    <desc></desc>
  </programme>
  <programme start="20260704000000 +0800" stop="20260704021500 +0800" channel="LS-Time電影台">
    <title>父女變錯身</title>
    <desc></desc>
  </programme>
  <programme start="20260704000000 +0800" stop="20260704011000 +0800" channel="LS-Time電影台">
    <title>無節目資料</title>
    <desc></desc>
  </programme>
  <programme start="20260704011000 +0800" stop="20260704030000 +0800" channel="LS-Time電影台">
    <title>人肉香腸</title>
    <desc></desc>
  </programme>
  <programme start="20260704030000 +0800" stop="20260704050000 +0800" channel="LS-Time電影台">
    <title>互動殺人事件</title>
    <desc></desc>
  </programme>
  <programme start="20260704050000 +0800" stop="20260704070500 +0800" channel="LS-Time電影台">
    <title>鎗王</title>
    <desc></desc>
  </programme>
  <programme start="20260704070500 +0800" stop="20260704102000 +0800" channel="LS-Time電影台">
    <title>宋家皇朝</title>
    <desc></desc>
  </programme>
  <programme start="20260704102000 +0800" stop="20260704130500 +0800" channel="LS-Time電影台">
    <title>夜宴</title>
    <desc></desc>
  </programme>
  <programme start="20260704130500 +0800" stop="20260704153500 +0800" channel="LS-Time電影台">
    <title>南海十三郎</title>
    <desc></desc>
  </programme>
  <programme start="20260704153500 +0800" stop="20260704181000 +0800" channel="LS-Time電影台">
    <title>我知女人心</title>
    <desc></desc>
  </programme>
  <programme start="20260704181000 +0800" stop="20260704210000 +0800" channel="LS-Time電影台">
    <title>賭神</title>
    <desc></desc>
  </programme>
  <programme start="20260704210000 +0800" stop="20260704234000 +0800" channel="LS-Time電影台">
    <title>電影版 嬌妻出沒注意</title>
    <desc></desc>
  </programme>
  <programme start="20260704235000 +0800" stop="20260705000000 +0800" channel="LS-Time電影台">
    <title>猜猜我是誰</title>
    <desc></desc>
  </programme>
  <programme start="20260705000000 +0800" stop="20260705023000 +0800" channel="LS-Time電影台">
    <title>猜猜我是誰</title>
    <desc></desc>
  </programme>
  <programme start="20260705000000 +0800" stop="20260705021500 +0800" channel="LS-Time電影台">
    <title>無節目資料</title>
    <desc></desc>
  </programme>
  <programme start="20260705021500 +0800" stop="20260705042000 +0800" channel="LS-Time電影台">
    <title>群龍戲鳳</title>
    <desc></desc>
  </programme>
  <programme start="20260705042000 +0800" stop="20260705065500 +0800" channel="LS-Time電影台">
    <title>緊急迫降</title>
    <desc></desc>
  </programme>
  <programme start="20260705065500 +0800" stop="20260705094000 +0800" channel="LS-Time電影台">
    <title>至尊無上</title>
    <desc></desc>
  </programme>
  <programme start="20260705094000 +0800" stop="20260705120500 +0800" channel="LS-Time電影台">
    <title>喋血雙雄</title>
    <desc></desc>
  </programme>
  <programme start="20260705120500 +0800" stop="20260705143000 +0800" channel="LS-Time電影台">
    <title>暴龍誕生</title>
    <desc></desc>
  </programme>
  <programme start="20260705143000 +0800" stop="20260705162500 +0800" channel="LS-Time電影台">
    <title>新暫時停止呼吸</title>
    <desc></desc>
  </programme>
  <programme start="20260705162500 +0800" stop="20260705182500 +0800" channel="LS-Time電影台">
    <title>螢火蟲之墓</title>
    <desc></desc>
  </programme>
  <programme start="20260705182500 +0800" stop="20260705210000 +0800" channel="LS-Time電影台">
    <title>別叫我賭神</title>
    <desc></desc>
  </programme>
  <programme start="20260705210000 +0800" stop="20260705235000 +0800" channel="LS-Time電影台">
    <title>電影版 TOKYO MER-行動急診室</title>
    <desc></desc>
  </programme>
  <channel id="天映頻道">
    <display-name>天映頻道</display-name>
  </channel>
  <programme start="20260629000000 +0800" stop="20260629005000 +0800" channel="天映頻道">
    <title>無節目資料</title>
    <desc></desc>
  </programme>
  <programme start="20260629005000 +0800" stop="20260629025000 +0800" channel="天映頻道">
    <title>我談的那場戀愛</title>
    <desc>婦科名醫餘笑琴抱著一試無妨的心態下載交友軟體，卻在網上邂逅一位自稱法籍工程師的對象。殊不知，這位元物件其實是一名綽號「少年」的新手騙子，並且是網路詐騙集團的一員。隨著時間流逝，少年的愧疚感與笑琴的期望日益增強，這段關係愈演愈烈，真假難以區分。</desc>
  </programme>
  <programme start="20260629025000 +0800" stop="20260629045000 +0800" channel="天映頻道">
    <title>飯戲攻心</title>
    <desc>本喜劇的三兄弟同住在已故父母所留給他們的屋簷下。大哥堅持每晚都要一家人一起吃飯，而當他們開始邀請各自的女朋友同住時，關係也變得非常緊張，從而引發出愛情與友情的矛盾和妒忌，及各種錯綜複雜的感情問題。六位主角將一同飯戲攻心！</desc>
  </programme>
  <programme start="20260629045000 +0800" stop="20260629063500 +0800" channel="天映頻道">
    <title>手捲煙</title>
    <desc>退役華籍英軍關超收留為躲避仇人的南亞裔流氓文尼。文尼身上藏有偷來的毒品，導致關超亦被黑幫追捕。兩人住在同一屋簷下，縱有文化及種族的差異，但他們竟轉化為相知相遇的好朋友，更成為一對忠誠的好兄弟。</desc>
  </programme>
  <programme start="20260629063500 +0800" stop="20260629090000 +0800" channel="天映頻道">
    <title>少年的你</title>
    <desc>本片入圍角逐奧斯卡最佳國際影片獎。當陳念忙著面對高考的壓力時，卻被同學的霸淩煎熬。命運使陳念遇上邊緣少年小北，二人正要重過新生活時，不幸捲入一宗謀殺案中，亦因此改變了他們的一生。</desc>
  </programme>
  <programme start="20260629090000 +0800" stop="20260629105500 +0800" channel="天映頻道">
    <title>小曉</title>
    <desc>小曉是一個患有過度活躍症的女孩，在學校經常遭到同學的霸淩。她的父親在國外辛勤工作，而母親則認為她總是製造麻煩。唯有班導保羅似乎能理解她的困擾，並舒緩她的情緒。某個颱風夜晚，小曉目睹了媽媽與保羅之間的秘密。此時，她不僅要面對自己複雜的情感，還感受到人生的無助與孤獨。</desc>
  </programme>
  <programme start="20260629105500 +0800" stop="20260629123000 +0800" channel="天映頻道">
    <title>熱血燃燒</title>
    <desc>緝毒隊成員泰樺、老米、阿峰和阿棠共同參與抓捕毒梟的行動。然而，因黑警洩密，阿峰遇難，上司犧牲，阿棠也隨之消失。為了揭開真相，泰樺與老米在剿滅毒梟的過程中，必須在忠誠與背叛之間掙扎。</desc>
  </programme>
  <programme start="20260629123000 +0800" stop="20260629142500 +0800" channel="天映頻道">
    <title>孤星計劃</title>
    <desc>白色恐怖籠罩的1920年代上海，特工李一民肩負護送關鍵人物脫險的絕密任務。在孤立無援、步步追殺中，他與舊日同伴重逢，聯手突圍敵人的重重陷阱。一群熱血理想青年亦投身其中，在動盪時代中以犧牲與信念守護使命，找尋屬於自己的勇氣與方向。</desc>
  </programme>
  <programme start="20260629142500 +0800" stop="20260629164500 +0800" channel="天映頻道">
    <title>莫斯科行動</title>
    <desc>根據1993年「中俄列車大劫案」的真實故事改編，講述一群匪徒如何持械行劫，從過境列車中搶走現金及貨物。一名偽裝成商人的中國員警率領這次逮捕行動，當中卻揭發另一個更龐大的陰謀…</desc>
  </programme>
  <programme start="20260629164500 +0800" stop="20260629184000 +0800" channel="天映頻道">
    <title>不日成婚</title>
    <desc>阿佳與可怡在一個婚禮上相識，兩人一拍即合，相愛五年，終於迎來最大的感情危機－「結婚」！女方視結婚為愛的證明，男方則視結婚為愛的墳墓。二人能否解決雙方在結婚問題的矛盾? 最後又能否成婚?</desc>
  </programme>
  <programme start="20260629184000 +0800" stop="20260629210000 +0800" channel="天映頻道">
    <title>海角七號</title>
    <desc>一位台灣歌手要將七封送錯地址的久遠情書送到收件人友子手中。當他愛上也名叫友子的年輕日藉模特兒時，隨即發現當中偶然的時空連繫。</desc>
  </programme>
  <programme start="20260629210000 +0800" stop="20260629224500 +0800" channel="天映頻道">
    <title>拳道</title>
    <desc>阿牛從小向拳館師傅興叔拜師學拳，自始每逢遇到有人受到欺淩，他都會出手教訓壞人，並藉此鍛煉拳術。不久因拳館收入大減，興叔的兒子為維持拳館生計竟答應為對頭拳館運毒，卻因交易失敗被打至不成人形。阿牛為了替他報仇，決定殺上擂臺上決一死戰。</desc>
  </programme>
  <programme start="20260629224500 +0800" stop="20260630000000 +0800" channel="天映頻道">
    <title>拯救嫌疑人</title>
    <desc>女律師陳智琪在女兒被綁架後，接到神秘電話要求她為一位元謀殺案嫌疑犯辯護，只有官司勝訴後才可救回女兒。陳智琪聯同警員展開調查並找出證據，最終成功揭露事情的真相及幕後黑手的身份。陳智琪最後能否及時營救女兒？</desc>
  </programme>
  <programme start="20260630000000 +0800" stop="20260630004500 +0800" channel="天映頻道">
    <title>拯救嫌疑人</title>
    <desc>女律師陳智琪在女兒被綁架後，接到神秘電話要求她為一位元謀殺案嫌疑犯辯護，只有官司勝訴後才可救回女兒。陳智琪聯同警員展開調查並找出證據，最終成功揭露事情的真相及幕後黑手的身份。陳智琪最後能否及時營救女兒？</desc>
  </programme>
</tv>