<?xml version='1.0' encoding='utf-8'?>
<tv>
  <channel id="龍華卡通台">
    <display-name>龍華卡通台</display-name>
  </channel>
  <programme start="20251130233000 +0800" stop="20251201000000 +0800" channel="龍華卡通台">
    <title>旗旗號巡洋艦S1</title>
    <desc></desc>
  </programme>
  <programme start="20251201000000 +0800" stop="20251201003000 +0800" channel="龍華卡通台">
    <title>往哪跑！</title>
    <desc></desc>
  </programme>
  <programme start="20251201003000 +0800" stop="20251201010000 +0800" channel="龍華卡通台">
    <title>往哪跑！</title>
    <desc></desc>
  </programme>
  <programme start="20251201010000 +0800" stop="20251201013000 +0800" channel="龍華卡通台">
    <title>哈皮樂奇鬧翻天</title>
    <desc></desc>
  </programme>
  <programme start="20251201013000 +0800" stop="20251201020000 +0800" channel="龍華卡通台">
    <title>哈皮樂奇鬧翻天</title>
    <desc></desc>
  </programme>
  <programme start="20251201020000 +0800" stop="20251201023000 +0800" channel="龍華卡通台">
    <title>功夫莫特</title>
    <desc></desc>
  </programme>
  <programme start="20251201023000 +0800" stop="20251201030000 +0800" channel="龍華卡通台">
    <title>功夫莫特</title>
    <desc></desc>
  </programme>
  <programme start="20251201030000 +0800" stop="20251201033000 +0800" channel="龍華卡通台">
    <title>往哪跑！</title>
    <desc></desc>
  </programme>
  <programme start="20251201033000 +0800" stop="20251201040000 +0800" channel="龍華卡通台">
    <title>往哪跑！</title>
    <desc></desc>
  </programme>
  <programme start="20251201040000 +0800" stop="20251201043000 +0800" channel="龍華卡通台">
    <title>哈皮樂奇鬧翻天</title>
    <desc></desc>
  </programme>
  <programme start="20251201043000 +0800" stop="20251201050000 +0800" channel="龍華卡通台">
    <title>哈皮樂奇鬧翻天</title>
    <desc></desc>
  </programme>
  <programme start="20251201050000 +0800" stop="20251201053000 +0800" channel="龍華卡通台">
    <title>功夫莫特</title>
    <desc></desc>
  </programme>
  <programme start="20251201053000 +0800" stop="20251201060000 +0800" channel="龍華卡通台">
    <title>功夫莫特</title>
    <desc></desc>
  </programme>
  <programme start="20251201060000 +0800" stop="20251201063000 +0800" channel="龍華卡通台">
    <title>往哪跑！</title>
    <desc></desc>
  </programme>
  <programme start="20251201063000 +0800" stop="20251201070000 +0800" channel="龍華卡通台">
    <title>往哪跑！</title>
    <desc></desc>
  </programme>
  <programme start="20251201070000 +0800" stop="20251201073000 +0800" channel="龍華卡通台">
    <title>哈皮樂奇鬧翻天</title>
    <desc></desc>
  </programme>
  <programme start="20251201073000 +0800" stop="20251201080000 +0800" channel="龍華卡通台">
    <title>哈皮樂奇鬧翻天</title>
    <desc></desc>
  </programme>
  <programme start="20251201080000 +0800" stop="20251201083000 +0800" channel="龍華卡通台">
    <title>功夫莫特</title>
    <desc></desc>
  </programme>
  <programme start="20251201083000 +0800" stop="20251201090000 +0800" channel="龍華卡通台">
    <title>功夫莫特</title>
    <desc></desc>
  </programme>
  <programme start="20251201090000 +0800" stop="20251201093000 +0800" channel="龍華卡通台">
    <title>往哪跑！</title>
    <desc></desc>
  </programme>
  <programme start="20251201093000 +0800" stop="20251201100000 +0800" channel="龍華卡通台">
    <title>往哪跑！</title>
    <desc></desc>
  </programme>
  <programme start="20251201100000 +0800" stop="20251201103000 +0800" channel="龍華卡通台">
    <title>哈皮樂奇鬧翻天</title>
    <desc></desc>
  </programme>
  <programme start="20251201103000 +0800" stop="20251201110000 +0800" channel="龍華卡通台">
    <title>哈皮樂奇鬧翻天</title>
    <desc></desc>
  </programme>
  <programme start="20251201110000 +0800" stop="20251201113000 +0800" channel="龍華卡通台">
    <title>功夫莫特</title>
    <desc></desc>
  </programme>
  <programme start="20251201113000 +0800" stop="20251201120000 +0800" channel="龍華卡通台">
    <title>功夫莫特</title>
    <desc></desc>
  </programme>
  <programme start="20251201120000 +0800" stop="20251201123000 +0800" channel="龍華卡通台">
    <title>往哪跑！</title>
    <desc></desc>
  </programme>
  <programme start="20251201123000 +0800" stop="20251201130000 +0800" channel="龍華卡通台">
    <title>往哪跑！</title>
    <desc></desc>
  </programme>
  <programme start="20251201130000 +0800" stop="20251201133000 +0800" channel="龍華卡通台">
    <title>哈皮樂奇鬧翻天</title>
    <desc></desc>
  </programme>
  <programme start="20251201133000 +0800" stop="20251201140000 +0800" channel="龍華卡通台">
    <title>哈皮樂奇鬧翻天</title>
    <desc></desc>
  </programme>
  <programme start="20251201140000 +0800" stop="20251201143000 +0800" channel="龍華卡通台">
    <title>功夫莫特</title>
    <desc></desc>
  </programme>
  <programme start="20251201143000 +0800" stop="20251201150000 +0800" channel="龍華卡通台">
    <title>功夫莫特</title>
    <desc></desc>
  </programme>
  <programme start="20251201150000 +0800" stop="20251201153000 +0800" channel="龍華卡通台">
    <title>往哪跑！</title>
    <desc></desc>
  </programme>
  <programme start="20251201153000 +0800" stop="20251201160000 +0800" channel="龍華卡通台">
    <title>往哪跑！</title>
    <desc></desc>
  </programme>
  <programme start="20251201160000 +0800" stop="20251201163000 +0800" channel="龍華卡通台">
    <title>哈皮樂奇鬧翻天</title>
    <desc></desc>
  </programme>
  <programme start="20251201163000 +0800" stop="20251201170000 +0800" channel="龍華卡通台">
    <title>哈皮樂奇鬧翻天</title>
    <desc></desc>
  </programme>
  <programme start="20251201170000 +0800" stop="20251201173000 +0800" channel="龍華卡通台">
    <title>功夫莫特</title>
    <desc></desc>
  </programme>
  <programme start="20251201173000 +0800" stop="20251201180000 +0800" channel="龍華卡通台">
    <title>功夫莫特</title>
    <desc></desc>
  </programme>
  <programme start="20251201180000 +0800" stop="20251201183000 +0800" channel="龍華卡通台">
    <title>往哪跑！</title>
    <desc></desc>
  </programme>
  <programme start="20251201183000 +0800" stop="20251201190000 +0800" channel="龍華卡通台">
    <title>往哪跑！</title>
    <desc></desc>
  </programme>
  <programme start="20251201190000 +0800" stop="20251201193000 +0800" channel="龍華卡通台">
    <title>哈皮樂奇鬧翻天</title>
    <desc></desc>
  </programme>
  <programme start="20251201193000 +0800" stop="20251201200000 +0800" channel="龍華卡通台">
    <title>哈皮樂奇鬧翻天</title>
    <desc></desc>
  </programme>
  <programme start="20251201200000 +0800" stop="20251201203000 +0800" channel="龍華卡通台">
    <title>功夫莫特</title>
    <desc></desc>
  </programme>
  <programme start="20251201203000 +0800" stop="20251201210000 +0800" channel="龍華卡通台">
    <title>功夫莫特</title>
    <desc></desc>
  </programme>
  <programme start="20251201210000 +0800" stop="20251201213000 +0800" channel="龍華卡通台">
    <title>往哪跑！</title>
    <desc></desc>
  </programme>
  <programme start="20251201213000 +0800" stop="20251201220000 +0800" channel="龍華卡通台">
    <title>往哪跑！</title>
    <desc></desc>
  </programme>
  <programme start="20251201220000 +0800" stop="20251201223000 +0800" channel="龍華卡通台">
    <title>哈皮樂奇鬧翻天</title>
    <desc></desc>
  </programme>
  <programme start="20251201223000 +0800" stop="20251201230000 +0800" channel="龍華卡通台">
    <title>哈皮樂奇鬧翻天</title>
    <desc></desc>
  </programme>
  <programme start="20251201230000 +0800" stop="20251201233000 +0800" channel="龍華卡通台">
    <title>功夫莫特</title>
    <desc></desc>
  </programme>
  <programme start="20251201233000 +0800" stop="20251202000000 +0800" channel="龍華卡通台">
    <title>功夫莫特</title>
    <desc></desc>
  </programme>
  <channel id="龍華日韓台">
    <display-name>龍華日韓台</display-name>
  </channel>
  <programme start="20251130220000 +0800" stop="20251201000000 +0800" channel="龍華日韓台">
    <title>最佳愛情</title>
    <desc></desc>
  </programme>
  <programme start="20251201000000 +0800" stop="20251201020000 +0800" channel="龍華日韓台">
    <title>燦爛的風和海</title>
    <desc></desc>
  </programme>
  <programme start="20251201020000 +0800" stop="20251201030000 +0800" channel="龍華日韓台">
    <title>陌生人</title>
    <desc></desc>
  </programme>
  <programme start="20251201030000 +0800" stop="20251201040000 +0800" channel="龍華日韓台">
    <title>榴蓮小姐</title>
    <desc></desc>
  </programme>
  <programme start="20251201040000 +0800" stop="20251201060000 +0800" channel="龍華日韓台">
    <title>歐若拉公主</title>
    <desc></desc>
  </programme>
  <programme start="20251201060000 +0800" stop="20251201080000 +0800" channel="龍華日韓台">
    <title>紅色高跟鞋</title>
    <desc></desc>
  </programme>
  <programme start="20251201080000 +0800" stop="20251201100000 +0800" channel="龍華日韓台">
    <title>歐若拉公主</title>
    <desc></desc>
  </programme>
  <programme start="20251201100000 +0800" stop="20251201120000 +0800" channel="龍華日韓台">
    <title>陌生人</title>
    <desc></desc>
  </programme>
  <programme start="20251201120000 +0800" stop="20251201140000 +0800" channel="龍華日韓台">
    <title>紅色高跟鞋</title>
    <desc></desc>
  </programme>
  <programme start="20251201140000 +0800" stop="20251201160000 +0800" channel="龍華日韓台">
    <title>燦爛的風和海</title>
    <desc></desc>
  </programme>
  <programme start="20251201160000 +0800" stop="20251201170000 +0800" channel="龍華日韓台">
    <title>榴蓮小姐</title>
    <desc></desc>
  </programme>
  <programme start="20251201170000 +0800" stop="20251201190000 +0800" channel="龍華日韓台">
    <title>歐若拉公主</title>
    <desc></desc>
  </programme>
  <programme start="20251201190000 +0800" stop="20251201200000 +0800" channel="龍華日韓台">
    <title>陌生人</title>
    <desc></desc>
  </programme>
  <programme start="20251201200000 +0800" stop="20251201220000 +0800" channel="龍華日韓台">
    <title>紅色高跟鞋</title>
    <desc></desc>
  </programme>
  <programme start="20251201220000 +0800" stop="20251201230000 +0800" channel="龍華日韓台">
    <title>陌生人</title>
    <desc></desc>
  </programme>
  <programme start="20251201230000 +0800" stop="20251202000000 +0800" channel="龍華日韓台">
    <title>榴蓮小姐</title>
    <desc></desc>
  </programme>
  <channel id="龍華偶像台">
    <display-name>龍華偶像台</display-name>
  </channel>
  <programme start="20251130220000 +0800" stop="20251201000000 +0800" channel="龍華偶像台">
    <title>暖陽之下</title>
    <desc></desc>
  </programme>
  <programme start="20251201000000 +0800" stop="20251201020000 +0800" channel="龍華偶像台">
    <title>善德女王</title>
    <desc></desc>
  </programme>
  <programme start="20251201020000 +0800" stop="20251201030000 +0800" channel="龍華偶像台">
    <title>Remember-兒子的戰爭</title>
    <desc></desc>
  </programme>
  <programme start="20251201030000 +0800" stop="20251201040000 +0800" channel="龍華偶像台">
    <title>兩個人的小森林</title>
    <desc></desc>
  </programme>
  <programme start="20251201040000 +0800" stop="20251201060000 +0800" channel="龍華偶像台">
    <title>善德女王</title>
    <desc></desc>
  </programme>
  <programme start="20251201060000 +0800" stop="20251201080000 +0800" channel="龍華偶像台">
    <title>玉面桃花總相逢</title>
    <desc></desc>
  </programme>
  <programme start="20251201080000 +0800" stop="20251201090000 +0800" channel="龍華偶像台">
    <title>Remember-兒子的戰爭</title>
    <desc></desc>
  </programme>
  <programme start="20251201090000 +0800" stop="20251201110000 +0800" channel="龍華偶像台">
    <title>善德女王</title>
    <desc></desc>
  </programme>
  <programme start="20251201110000 +0800" stop="20251201120000 +0800" channel="龍華偶像台">
    <title>兩個人的小森林</title>
    <desc></desc>
  </programme>
  <programme start="20251201120000 +0800" stop="20251201140000 +0800" channel="龍華偶像台">
    <title>玉面桃花總相逢</title>
    <desc></desc>
  </programme>
  <programme start="20251201140000 +0800" stop="20251201150000 +0800" channel="龍華偶像台">
    <title>Remember-兒子的戰爭</title>
    <desc></desc>
  </programme>
  <programme start="20251201150000 +0800" stop="20251201160000 +0800" channel="龍華偶像台">
    <title>Remember-兒子的戰爭</title>
    <desc></desc>
  </programme>
  <programme start="20251201160000 +0800" stop="20251201180000 +0800" channel="龍華偶像台">
    <title>善德女王</title>
    <desc></desc>
  </programme>
  <programme start="20251201180000 +0800" stop="20251201200000 +0800" channel="龍華偶像台">
    <title>玉面桃花總相逢</title>
    <desc></desc>
  </programme>
  <programme start="20251201200000 +0800" stop="20251201210000 +0800" channel="龍華偶像台">
    <title>Remember-兒子的戰爭</title>
    <desc></desc>
  </programme>
  <programme start="20251201210000 +0800" stop="20251201220000 +0800" channel="龍華偶像台">
    <title>兩個人的小森林</title>
    <desc></desc>
  </programme>
  <programme start="20251201220000 +0800" stop="20251202000000 +0800" channel="龍華偶像台">
    <title>玉面桃花總相逢</title>
    <desc></desc>
  </programme>
  <channel id="LS-Time電影台">
    <display-name>LS-Time電影台</display-name>
  </channel>
  <programme start="20251201000000 +0800" stop="20251201023000 +0800" channel="LS-Time電影台">
    <title>無節目資料</title>
    <desc></desc>
  </programme>
  <programme start="20251201023000 +0800" stop="20251201045000 +0800" channel="LS-Time電影台">
    <title>北京樂與路</title>
    <desc></desc>
  </programme>
  <programme start="20251201023000 +0800" stop="20251201065000 +0800" channel="LS-Time電影台">
    <title>白色榮光</title>
    <desc></desc>
  </programme>
  <programme start="20251201045000 +0800" stop="20251201065000 +0800" channel="LS-Time電影台">
    <title>橫財三千萬</title>
    <desc></desc>
  </programme>
  <programme start="20251201065000 +0800" stop="20251201085500 +0800" channel="LS-Time電影台">
    <title>猛鬼入侵黑社會</title>
    <desc></desc>
  </programme>
  <programme start="20251201065000 +0800" stop="20251201090500 +0800" channel="LS-Time電影台">
    <title>娘砲足球隊</title>
    <desc></desc>
  </programme>
  <programme start="20251201085500 +0800" stop="20251201105000 +0800" channel="LS-Time電影台">
    <title>山雞變鳳凰</title>
    <desc></desc>
  </programme>
  <programme start="20251201090500 +0800" stop="20251201112500 +0800" channel="LS-Time電影台">
    <title>六度空間大水怪</title>
    <desc></desc>
  </programme>
  <programme start="20251201105000 +0800" stop="20251201124500 +0800" channel="LS-Time電影台">
    <title>出水芙蓉</title>
    <desc></desc>
  </programme>
  <programme start="20251201112500 +0800" stop="20251201135000 +0800" channel="LS-Time電影台">
    <title>港囧</title>
    <desc></desc>
  </programme>
  <programme start="20251201124500 +0800" stop="20251201145500 +0800" channel="LS-Time電影台">
    <title>異靈靈異</title>
    <desc></desc>
  </programme>
  <programme start="20251201135000 +0800" stop="20251201161500 +0800" channel="LS-Time電影台">
    <title>喋血雙雄</title>
    <desc></desc>
  </programme>
  <programme start="20251201145500 +0800" stop="20251201170500 +0800" channel="LS-Time電影台">
    <title>富貴逼人</title>
    <desc></desc>
  </programme>
  <programme start="20251201161500 +0800" stop="20251201182000 +0800" channel="LS-Time電影台">
    <title>工人皇帝</title>
    <desc></desc>
  </programme>
  <programme start="20251201170500 +0800" stop="20251201190500 +0800" channel="LS-Time電影台">
    <title>天生一條蟲</title>
    <desc></desc>
  </programme>
  <programme start="20251201182000 +0800" stop="20251201210000 +0800" channel="LS-Time電影台">
    <title>在咖啡冷掉之前</title>
    <desc></desc>
  </programme>
  <programme start="20251201190500 +0800" stop="20251201210000 +0800" channel="LS-Time電影台">
    <title>江湖接班人</title>
    <desc></desc>
  </programme>
  <programme start="20251201210000 +0800" stop="20251201232500 +0800" channel="LS-Time電影台">
    <title>神探蒲松齡</title>
    <desc></desc>
  </programme>
  <programme start="20251201210000 +0800" stop="20251201230500 +0800" channel="LS-Time電影台">
    <title>此心安處</title>
    <desc></desc>
  </programme>
  <programme start="20251201230500 +0800" stop="20251202000000 +0800" channel="LS-Time電影台">
    <title>鐵血騎警</title>
    <desc></desc>
  </programme>
  <programme start="20251201233500 +0800" stop="20251202000000 +0800" channel="LS-Time電影台">
    <title>風雲雄霸天下</title>
    <desc></desc>
  </programme>
  <programme start="20251202000000 +0800" stop="20251202011000 +0800" channel="LS-Time電影台">
    <title>鐵血騎警</title>
    <desc></desc>
  </programme>
  <programme start="20251202000000 +0800" stop="20251202022500 +0800" channel="LS-Time電影台">
    <title>風雲雄霸天下</title>
    <desc></desc>
  </programme>
  <programme start="20251202000000 +0800" stop="20251202012500 +0800" channel="LS-Time電影台">
    <title>無節目資料</title>
    <desc></desc>
  </programme>
  <programme start="20251202012500 +0800" stop="20251202033000 +0800" channel="LS-Time電影台">
    <title>豐胸奇緣之微波蕩漾</title>
    <desc></desc>
  </programme>
  <programme start="20251202013500 +0800" stop="20251202041500 +0800" channel="LS-Time電影台">
    <title>秘密</title>
    <desc></desc>
  </programme>
  <programme start="20251202033000 +0800" stop="20251202054000 +0800" channel="LS-Time電影台">
    <title>真心英雄</title>
    <desc></desc>
  </programme>
  <programme start="20251202041500 +0800" stop="20251202062000 +0800" channel="LS-Time電影台">
    <title>七月鬼門開</title>
    <desc></desc>
  </programme>
  <programme start="20251202054000 +0800" stop="20251202074500 +0800" channel="LS-Time電影台">
    <title>我要富貴</title>
    <desc></desc>
  </programme>
  <programme start="20251202062000 +0800" stop="20251202083500 +0800" channel="LS-Time電影台">
    <title>翻天鵝</title>
    <desc></desc>
  </programme>
  <programme start="20251202074500 +0800" stop="20251202095000 +0800" channel="LS-Time電影台">
    <title>阿飛正傳</title>
    <desc></desc>
  </programme>
  <programme start="20251202083500 +0800" stop="20251202111500 +0800" channel="LS-Time電影台">
    <title>玻璃樽</title>
    <desc></desc>
  </programme>
  <programme start="20251202095000 +0800" stop="20251202123500 +0800" channel="LS-Time電影台">
    <title>告別單身</title>
    <desc></desc>
  </programme>
  <programme start="20251202111500 +0800" stop="20251202133500 +0800" channel="LS-Time電影台">
    <title>龍虎風雲</title>
    <desc></desc>
  </programme>
  <programme start="20251202123500 +0800" stop="20251202145000 +0800" channel="LS-Time電影台">
    <title>搶錢夫妻</title>
    <desc></desc>
  </programme>
  <programme start="20251202133500 +0800" stop="20251202160000 +0800" channel="LS-Time電影台">
    <title>紫雨風暴</title>
    <desc></desc>
  </programme>
  <programme start="20251202145000 +0800" stop="20251202165500 +0800" channel="LS-Time電影台">
    <title>超級學校霸王</title>
    <desc></desc>
  </programme>
  <programme start="20251202160000 +0800" stop="20251202180500 +0800" channel="LS-Time電影台">
    <title>老鼠愛上貓</title>
    <desc></desc>
  </programme>
  <programme start="20251202165500 +0800" stop="20251202185500 +0800" channel="LS-Time電影台">
    <title>創業玩家</title>
    <desc></desc>
  </programme>
  <programme start="20251202180500 +0800" stop="20251202210000 +0800" channel="LS-Time電影台">
    <title>三城記</title>
    <desc></desc>
  </programme>
  <programme start="20251202185500 +0800" stop="20251202210000 +0800" channel="LS-Time電影台">
    <title>新仙鶴神針</title>
    <desc></desc>
  </programme>
  <programme start="20251202210000 +0800" stop="20251202230500 +0800" channel="LS-Time電影台">
    <title>不可思異</title>
    <desc></desc>
  </programme>
  <programme start="20251202210000 +0800" stop="20251202233500 +0800" channel="LS-Time電影台">
    <title>八百壯士</title>
    <desc></desc>
  </programme>
  <programme start="20251202230000 +0800" stop="20251203000000 +0800" channel="LS-Time電影台">
    <title>菜鳥警校生</title>
    <desc></desc>
  </programme>
  <programme start="20251203000000 +0800" stop="20251203012500 +0800" channel="LS-Time電影台">
    <title>菜鳥警校生</title>
    <desc></desc>
  </programme>
  <programme start="20251203000000 +0800" stop="20251203011000 +0800" channel="LS-Time電影台">
    <title>無節目資料</title>
    <desc></desc>
  </programme>
  <programme start="20251203011000 +0800" stop="20251203031500 +0800" channel="LS-Time電影台">
    <title>小生發威</title>
    <desc></desc>
  </programme>
  <programme start="20251203031500 +0800" stop="20251203053500 +0800" channel="LS-Time電影台">
    <title>放逐</title>
    <desc></desc>
  </programme>
  <programme start="20251203053500 +0800" stop="20251203082000 +0800" channel="LS-Time電影台">
    <title>消失的她</title>
    <desc></desc>
  </programme>
  <programme start="20251203082000 +0800" stop="20251203110500 +0800" channel="LS-Time電影台">
    <title>皇天后土</title>
    <desc></desc>
  </programme>
  <programme start="20251203110500 +0800" stop="20251203134000 +0800" channel="LS-Time電影台">
    <title>緊急迫降</title>
    <desc></desc>
  </programme>
  <programme start="20251203134000 +0800" stop="20251203163000 +0800" channel="LS-Time電影台">
    <title>天將雄師</title>
    <desc></desc>
  </programme>
  <programme start="20251203163000 +0800" stop="20251203183000 +0800" channel="LS-Time電影台">
    <title>麻吉妖怪島</title>
    <desc></desc>
  </programme>
  <programme start="20251203183000 +0800" stop="20251203210000 +0800" channel="LS-Time電影台">
    <title>通靈少年2020</title>
    <desc></desc>
  </programme>
  <programme start="20251203210000 +0800" stop="20251203230000 +0800" channel="LS-Time電影台">
    <title>冤鴦大盜</title>
    <desc></desc>
  </programme>
  <programme start="20251203230500 +0800" stop="20251204000000 +0800" channel="LS-Time電影台">
    <title>常在你左右</title>
    <desc></desc>
  </programme>
  <programme start="20251204000000 +0800" stop="20251204012000 +0800" channel="LS-Time電影台">
    <title>常在你左右</title>
    <desc></desc>
  </programme>
  <programme start="20251204000000 +0800" stop="20251204012500 +0800" channel="LS-Time電影台">
    <title>無節目資料</title>
    <desc></desc>
  </programme>
  <programme start="20251204012500 +0800" stop="20251204040500 +0800" channel="LS-Time電影台">
    <title>第三凶間</title>
    <desc></desc>
  </programme>
  <programme start="20251204040500 +0800" stop="20251204065000 +0800" channel="LS-Time電影台">
    <title>我的野蠻女友2-蠻風再現</title>
    <desc></desc>
  </programme>
  <programme start="20251204065000 +0800" stop="20251204094500 +0800" channel="LS-Time電影台">
    <title>新少林寺</title>
    <desc></desc>
  </programme>
  <programme start="20251204094500 +0800" stop="20251204121500 +0800" channel="LS-Time電影台">
    <title>再戰江湖</title>
    <desc></desc>
  </programme>
  <programme start="20251204121500 +0800" stop="20251204145000 +0800" channel="LS-Time電影台">
    <title>無家可歸的中學生</title>
    <desc></desc>
  </programme>
  <programme start="20251204145000 +0800" stop="20251204165000 +0800" channel="LS-Time電影台">
    <title>開心鬼撞鬼</title>
    <desc></desc>
  </programme>
  <programme start="20251204165000 +0800" stop="20251204185500 +0800" channel="LS-Time電影台">
    <title>大佬愛美麗</title>
    <desc></desc>
  </programme>
  <programme start="20251204185500 +0800" stop="20251204210000 +0800" channel="LS-Time電影台">
    <title>霹靂大神探</title>
    <desc></desc>
  </programme>
  <programme start="20251204210000 +0800" stop="20251204230500 +0800" channel="LS-Time電影台">
    <title>總是有愛在隔離</title>
    <desc></desc>
  </programme>
  <programme start="20251204234500 +0800" stop="20251205000000 +0800" channel="LS-Time電影台">
    <title>荷魯斯之眼-王者爭霸</title>
    <desc></desc>
  </programme>
  <programme start="20251205000000 +0800" stop="20251205023500 +0800" channel="LS-Time電影台">
    <title>荷魯斯之眼-王者爭霸</title>
    <desc></desc>
  </programme>
  <programme start="20251205000000 +0800" stop="20251205012000 +0800" channel="LS-Time電影台">
    <title>無節目資料</title>
    <desc></desc>
  </programme>
  <programme start="20251205012000 +0800" stop="20251205035000 +0800" channel="LS-Time電影台">
    <title>功夫棒球</title>
    <desc></desc>
  </programme>
  <programme start="20251205035000 +0800" stop="20251205055000 +0800" channel="LS-Time電影台">
    <title>創業玩家</title>
    <desc></desc>
  </programme>
  <programme start="20251205055000 +0800" stop="20251205080000 +0800" channel="LS-Time電影台">
    <title>洗黑錢</title>
    <desc></desc>
  </programme>
  <programme start="20251205080000 +0800" stop="20251205105000 +0800" channel="LS-Time電影台">
    <title>五億探長雷洛傳</title>
    <desc></desc>
  </programme>
  <programme start="20251205105000 +0800" stop="20251205134000 +0800" channel="LS-Time電影台">
    <title>風雲雄霸天下</title>
    <desc></desc>
  </programme>
  <programme start="20251205134000 +0800" stop="20251205164000 +0800" channel="LS-Time電影台">
    <title>日本沉沒</title>
    <desc></desc>
  </programme>
  <programme start="20251205164000 +0800" stop="20251205185000 +0800" channel="LS-Time電影台">
    <title>又見阿郎</title>
    <desc></desc>
  </programme>
  <programme start="20251205185000 +0800" stop="20251205210500 +0800" channel="LS-Time電影台">
    <title>超跑斯特拉</title>
    <desc></desc>
  </programme>
  <programme start="20251205210500 +0800" stop="20251205234500 +0800" channel="LS-Time電影台">
    <title>龍門飛甲</title>
    <desc></desc>
  </programme>
  <programme start="20251205235000 +0800" stop="20251206000000 +0800" channel="LS-Time電影台">
    <title>消失的她</title>
    <desc></desc>
  </programme>
  <programme start="20251206000000 +0800" stop="20251206023000 +0800" channel="LS-Time電影台">
    <title>消失的她</title>
    <desc></desc>
  </programme>
  <programme start="20251206000000 +0800" stop="20251206023500 +0800" channel="LS-Time電影台">
    <title>無節目資料</title>
    <desc></desc>
  </programme>
  <programme start="20251206023500 +0800" stop="20251206052000 +0800" channel="LS-Time電影台">
    <title>天咒</title>
    <desc></desc>
  </programme>
  <programme start="20251206052000 +0800" stop="20251206073500 +0800" channel="LS-Time電影台">
    <title>隱婚男女</title>
    <desc></desc>
  </programme>
  <programme start="20251206073500 +0800" stop="20251206094000 +0800" channel="LS-Time電影台">
    <title>大佬鬥和尚</title>
    <desc></desc>
  </programme>
  <programme start="20251206094000 +0800" stop="20251206115000 +0800" channel="LS-Time電影台">
    <title>七福將</title>
    <desc></desc>
  </programme>
  <programme start="20251206115000 +0800" stop="20251206135500 +0800" channel="LS-Time電影台">
    <title>草莽英雌</title>
    <desc></desc>
  </programme>
  <programme start="20251206135500 +0800" stop="20251206160000 +0800" channel="LS-Time電影台">
    <title>淚眼煞星</title>
    <desc></desc>
  </programme>
  <programme start="20251206160000 +0800" stop="20251206182500 +0800" channel="LS-Time電影台">
    <title>唱吧！奇蹟！</title>
    <desc></desc>
  </programme>
  <programme start="20251206182500 +0800" stop="20251206210500 +0800" channel="LS-Time電影台">
    <title>笑傲江湖</title>
    <desc></desc>
  </programme>
  <programme start="20251206210500 +0800" stop="20251206235000 +0800" channel="LS-Time電影台">
    <title>李小龍</title>
    <desc></desc>
  </programme>
  <channel id="天映頻道">
    <display-name>天映頻道</display-name>
  </channel>
  <programme start="20251201000000 +0800" stop="20251201071300 +0800" channel="天映頻道">
    <title>無節目資料</title>
    <desc></desc>
  </programme>
  <programme start="20251201071300 +0800" stop="20251201090000 +0800" channel="天映頻道">
    <title>The Hedgehog</title>
    <desc>Wang's odd behaviour and quirky ideas make him a social outcast. His teenage nephew Zhou, who is ashamed of his stutter, becomes Wang's only friend. Together, these misfits challenge traditional family expectations and social misunderstandings, supporting and inspiring each other as they seek their own paths in life.</desc>
  </programme>
  <programme start="20251201090000 +0800" stop="20251201110800 +0800" channel="天映頻道">
    <title>Operation Mekong</title>
    <desc>After it is discovered that the drugs seized on the Chinese ships had been planted by the henchman of a notorious drug cartel leader named Naw Khar, the governments of Thailand, Laos, Myanmar and China launched a joint task force to apprehend the criminal by sending a band of elite narcotics officers to the Golden Triangle to uncover the truth.</desc>
  </programme>
  <programme start="20251201110800 +0800" stop="20251201124700 +0800" channel="天映頻道">
    <title>Shadows</title>
    <desc>Ching is a forensic psychiatrist who has the power to enter a person’s subconscious mind. In her latest case, she suspects that another psychiatrist is responsible for a brutal murder-cum-suicide case involving a social worker. In the investigation process, Ching finds herself under suspicion instead, as she comes face-to-face with a past trauma…</desc>
  </programme>
  <programme start="20251201124700 +0800" stop="20251201150300 +0800" channel="天映頻道">
    <title>Project Gutenberg</title>
    <desc>The Hong Kong Police hunts for a counterfeiting gang led by a mastermind known as Painter. The gang is so skillful that it's almost impossible to distinguish between its counterfeit currency and real money. In an effort to find Painter's real identity, the Police recruits artist Lee Man to assist in solving the case.</desc>
  </programme>
  <programme start="20251201150300 +0800" stop="20251201164900 +0800" channel="天映頻道">
    <title>My Best Bet</title>
    <desc>Gambling addict Jing vows to quit after marrying anti-gambling advocate Zheng. However, wealthy gambler Ian nurses a long-held grudge against Zheng over a past humiliation and exacts revenge by taking the couple’s siblings hostage. To save them, Jing breaks her vow and alongside Zheng, faces Ian in a final gamble.</desc>
  </programme>
  <programme start="20251201164900 +0800" stop="20251201184000 +0800" channel="天映頻道">
    <title>Wolf Hiding</title>
    <desc>A cold-blooded killer, Chen An vows to take revenge for her sister who was killed by a crime gang. Dealing with the police and the triad at the same time, a final battle between good and evil has just begun!</desc>
  </programme>
  <programme start="20251201184000 +0800" stop="20251201202000 +0800" channel="天映頻道">
    <title>Far Far Away</title>
    <desc>A 28-year-old IT geek has only been in love once. Surprisingly, he ends up getting romantically involved with five different women this year and the one thing they have in common is that they all live in far flung areas of Hong Kong. After taking five intensive relationship courses within these 365 days, will he find “the-one”?</desc>
  </programme>
  <programme start="20251201202000 +0800" stop="20251201220000 +0800" channel="天映頻道">
    <title>The Brotherhood of Rebel</title>
    <desc>Chai, a triad member, helps his childhood friend Meow flee Hong Kong after discovering that Meow attempted to kill his triad boss. 17 years later, Chai becomes a key member of the triad. When he runs into Meow one day, he knows that his gang will kill Meow if they find him. Caught between triad and brotherhood, what will Chai choose?</desc>
  </programme>
  <programme start="20251201220000 +0800" stop="20251201234600 +0800" channel="天映頻道">
    <title>American Girl</title>
    <desc>13 year-old Fen is uprooted from LA and moves to Taipei in early 2003, when her mother is diagnosed with breast cancer. She struggles to adjust to her new life with a new school and long-separated father, and drifts away from her mother. When her younger sister is misdiagnosed with SARS, they finally open up to each other during quarantine.</desc>
  </programme>
  <programme start="20251201234600 +0800" stop="20251202000000 +0800" channel="天映頻道">
    <title>Chasing the Dragon</title>
    <desc>Infamous real-life drug kingpin Crippled Ho came to Hong Kong as an illegal immigrant in 1963 and ruthlessly built an empire from the chaotic underworld of drug dealers and corrupt police who ruled the city under notorious detective Lee Rock.</desc>
  </programme>
  <programme start="20251202000000 +0800" stop="20251202024600 +0800" channel="天映頻道">
    <title>Chasing the Dragon</title>
    <desc>Infamous real-life drug kingpin Crippled Ho came to Hong Kong as an illegal immigrant in 1963 and ruthlessly built an empire from the chaotic underworld of drug dealers and corrupt police who ruled the city under notorious detective Lee Rock.</desc>
  </programme>
</tv>